vws/__init__.py
vws/include_target_data.py
vws/py.typed
vws/query.py
vws/reports.py
vws/response.py
vws/vws.py
vws/exceptions/__init__.py
vws/exceptions/base_exceptions.py
vws/exceptions/cloud_reco_exceptions.py
vws/exceptions/custom_exceptions.py
vws/exceptions/vws_exceptions.py
vws_python-2025.3.10.1.dist-info/LICENSE
vws_python-2025.3.10.1.dist-info/METADATA
vws_python-2025.3.10.1.dist-info/WHEEL
vws_python-2025.3.10.1.dist-info/top_level.txt
vws_python-2025.3.10.1.dist-info/RECORD
